ddn_metadata_bootstrap/__init__.py
ddn_metadata_bootstrap/__main__.py
ddn_metadata_bootstrap/bootstrapper.py
ddn_metadata_bootstrap/config.py
ddn_metadata_bootstrap/main.py
ddn_metadata_bootstrap/run.py
ddn_metadata_bootstrap/ai/__init__.py
ddn_metadata_bootstrap/ai/description_cache.py
ddn_metadata_bootstrap/ai/description_generator.py
ddn_metadata_bootstrap/ai/specificity.py
ddn_metadata_bootstrap/processors/__init__.py
ddn_metadata_bootstrap/processors/directory_processor.py
ddn_metadata_bootstrap/processors/document_enhancer.py
ddn_metadata_bootstrap/processors/file_processor.py
ddn_metadata_bootstrap/relationships/__init__.py
ddn_metadata_bootstrap/relationships/detector.py
ddn_metadata_bootstrap/relationships/generator.py
ddn_metadata_bootstrap/relationships/mapper.py
ddn_metadata_bootstrap/schema/__init__.py
ddn_metadata_bootstrap/schema/domain_analyzer.py
ddn_metadata_bootstrap/schema/field_analyzer.py
ddn_metadata_bootstrap/schema/metadata_collector.py
ddn_metadata_bootstrap/utils/__init__.py
ddn_metadata_bootstrap/utils/path_utils.py
ddn_metadata_bootstrap/utils/text_utils.py
ddn_metadata_bootstrap/utils/yaml_utils.py
ddn_metadata_bootstrap-1.0.13.dist-info/licenses/LICENSE
ddn_metadata_bootstrap-1.0.13.dist-info/METADATA
ddn_metadata_bootstrap-1.0.13.dist-info/WHEEL
ddn_metadata_bootstrap-1.0.13.dist-info/entry_points.txt
ddn_metadata_bootstrap-1.0.13.dist-info/top_level.txt
ddn_metadata_bootstrap-1.0.13.dist-info/RECORD
