Metadata-Version: 2.4
Name: ddn-metadata-bootstrap
Version: 1.0.13
Summary: AI-powered metadata enhancement for Hasura DDN schema files
Author-email: Kenneth Stott <kenneth@hasura.io>
Maintainer-email: Kenneth Stott <kenneth@hasura.io>
License: MIT
Project-URL: Homepage, https://github.com/hasura/ddn-metadata-bootstrap
Project-URL: Documentation, https://github.com/hasura/ddn-metadata-bootstrap#readme
Project-URL: Repository, https://github.com/hasura/ddn-metadata-bootstrap.git
Project-URL: Bug Reports, https://github.com/hasura/ddn-metadata-bootstrap/issues
Project-URL: Changelog, https://github.com/hasura/ddn-metadata-bootstrap/blob/main/CHANGELOG.md
Keywords: hasura,ddn,graphql,schema,metadata,ai,anthropic,descriptions,relationships
Classifier: Development Status :: 4 - Beta
Classifier: Intended Audience :: Developers
Classifier: License :: OSI Approved :: MIT License
Classifier: Operating System :: OS Independent
Classifier: Programming Language :: Python :: 3
Classifier: Programming Language :: Python :: 3.8
Classifier: Programming Language :: Python :: 3.9
Classifier: Programming Language :: Python :: 3.10
Classifier: Programming Language :: Python :: 3.11
Classifier: Programming Language :: Python :: 3.12
Classifier: Topic :: Software Development :: Libraries :: Python Modules
Classifier: Topic :: Database
Classifier: Topic :: Internet :: WWW/HTTP :: Dynamic Content
Classifier: Topic :: Software Development :: Code Generators
Requires-Python: >=3.8
License-File: LICENSE
Requires-Dist: anthropic>=0.3.0
Requires-Dist: PyYAML>=6.0
Requires-Dist: python-dotenv>=0.19.0
Requires-Dist: inflection>=0.5.1
Requires-Dist: nltk>=3.9.1
Requires-Dist: openai>=1.97.0
Requires-Dist: google-generativeai>=0.8.5
Provides-Extra: dev
Requires-Dist: pytest>=7.0.0; extra == "dev"
Requires-Dist: pytest-cov>=4.0.0; extra == "dev"
Requires-Dist: black>=22.0.0; extra == "dev"
Requires-Dist: flake8>=5.0.0; extra == "dev"
Requires-Dist: mypy>=1.0.0; extra == "dev"
Requires-Dist: twine>=4.0.0; extra == "dev"
Requires-Dist: build>=0.10.0; extra == "dev"
Requires-Dist: bump2version>=1.0.0; extra == "dev"
Provides-Extra: test
Requires-Dist: pytest>=7.0.0; extra == "test"
Requires-Dist: pytest-cov>=4.0.0; extra == "test"
Dynamic: license-file
